_api/__init__.py
_api/deprecation.py
_api/interactive_env.py
_api/module_import.py
_api/path.py
adapters/__init__.py
adapters/openai.py
agents/__init__.py
agents/agent.py
agents/agent_iterator.py
agents/agent_types.py
agents/initialize.py
agents/load_tools.py
agents/loading.py
agents/schema.py
agents/tools.py
agents/types.py
agents/utils.py
agents/agent_toolkits/__init__.py
agents/agent_toolkits/azure_cognitive_services.py
agents/agent_toolkits/base.py
agents/agent_toolkits/ainetwork/__init__.py
agents/agent_toolkits/ainetwork/toolkit.py
agents/agent_toolkits/clickup/__init__.py
agents/agent_toolkits/clickup/toolkit.py
agents/agent_toolkits/conversational_retrieval/__init__.py
agents/agent_toolkits/conversational_retrieval/openai_functions.py
agents/agent_toolkits/conversational_retrieval/tool.py
agents/agent_toolkits/csv/__init__.py
agents/agent_toolkits/file_management/__init__.py
agents/agent_toolkits/file_management/toolkit.py
agents/agent_toolkits/github/__init__.py
agents/agent_toolkits/github/toolkit.py
agents/agent_toolkits/gitlab/__init__.py
agents/agent_toolkits/gitlab/toolkit.py
agents/agent_toolkits/gmail/__init__.py
agents/agent_toolkits/gmail/toolkit.py
agents/agent_toolkits/jira/__init__.py
agents/agent_toolkits/jira/toolkit.py
agents/agent_toolkits/json/__init__.py
agents/agent_toolkits/json/base.py
agents/agent_toolkits/json/prompt.py
agents/agent_toolkits/json/toolkit.py
agents/agent_toolkits/multion/__init__.py
agents/agent_toolkits/multion/toolkit.py
agents/agent_toolkits/nasa/__init__.py
agents/agent_toolkits/nasa/toolkit.py
agents/agent_toolkits/nla/__init__.py
agents/agent_toolkits/nla/tool.py
agents/agent_toolkits/nla/toolkit.py
agents/agent_toolkits/office365/__init__.py
agents/agent_toolkits/office365/toolkit.py
agents/agent_toolkits/openapi/__init__.py
agents/agent_toolkits/openapi/base.py
agents/agent_toolkits/openapi/planner.py
agents/agent_toolkits/openapi/planner_prompt.py
agents/agent_toolkits/openapi/prompt.py
chainlang-0.1.dist-info/METADATA
chainlang-0.1.dist-info/WHEEL
chainlang-0.1.dist-info/top_level.txt
chainlang-0.1.dist-info/RECORD
