Metadata-Version: 2.1
Name: chainlang
Version: 0.1
Summary: Modified version of langchain that fix the bug of langchain agent tool
Home-page: https://github.com/vprashrex/chainlang.git
Author: Prashant
Author-email: vprashant5050@gmail.com
Classifier: Programming Language :: Python :: 3
Classifier: License :: OSI Approved :: MIT License
Classifier: Operating System :: OS Independent
Requires-Python: >=3.6
